{
    "card_id": "shady_trade_deal",
    "stable_id": 39,
    "name": "Shady Trade Deal",
    "card_type": "magic",
    "mana_cost": 1,
    "element": "dark",
    "discard_cost_tribe": "any",
    "discard_cost_count": 1,
    "effects": [
        {
            "type": "grant_dark_matter",
            "trigger": "on_play",
            "target": "all_allies",
            "target_tribe": "Mage",
            "amount": 1
        }
    ],
    "rulings": [
        "To play this card, you must discard one other card from your hand (any card, any type). The discarded card goes to the exhaust pile.",
        "Each friendly Mage on the board gains +1 Dark Matter. Mages in hand or deck are not affected.",
        "The discarded card may trigger its own on-discard effects (e.g. Dark Matter Stash grants Dark Matter to all Mages when discarded).",
        "If you have no other cards in hand, you cannot pay the discard cost and cannot play this card."
    ]
}
